station_service_sdk/__init__.py
station_service_sdk/context.py
station_service_sdk/exceptions.py
station_service_sdk/interfaces.py
station_service_sdk/manifest.py
station_service_sdk/py.typed
station_service_sdk/sdk_types.py
station_service_sdk/cli/__init__.py
station_service_sdk/cli/main.py
station_service_sdk/cli/commands/__init__.py
station_service_sdk/cli/commands/debug.py
station_service_sdk/cli/commands/deps.py
station_service_sdk/cli/commands/doctor.py
station_service_sdk/cli/commands/init.py
station_service_sdk/cli/commands/lint.py
station_service_sdk/cli/commands/new.py
station_service_sdk/cli/commands/run.py
station_service_sdk/cli/commands/validate.py
station_service_sdk/compat/__init__.py
station_service_sdk/compat/decorators.py
station_service_sdk/compat/dependencies.py
station_service_sdk/compat/legacy_cli.py
station_service_sdk/compat/sequence_cli.py
station_service_sdk/compat/types.py
station_service_sdk/core/__init__.py
station_service_sdk/core/base.py
station_service_sdk/core/context.py
station_service_sdk/core/exceptions.py
station_service_sdk/core/interfaces.py
station_service_sdk/core/manifest.py
station_service_sdk/core/protocol.py
station_service_sdk/core/sdk_types.py
station_service_sdk/core/types.py
station_service_sdk/core/validators.py
station_service_sdk/execution/__init__.py
station_service_sdk/execution/base.py
station_service_sdk/execution/context.py
station_service_sdk/execution/dependencies.py
station_service_sdk/execution/driver_registry.py
station_service_sdk/execution/exceptions.py
station_service_sdk/execution/helpers.py
station_service_sdk/execution/interactive.py
station_service_sdk/execution/interfaces.py
station_service_sdk/execution/loader.py
station_service_sdk/execution/manifest.py
station_service_sdk/execution/manual_executor.py
station_service_sdk/execution/registry.py
station_service_sdk/execution/simulator.py
station_service_sdk/execution/types.py
station_service_sdk/execution/validate.py
station_service_sdk-2.1.0.dist-info/METADATA
station_service_sdk-2.1.0.dist-info/WHEEL
station_service_sdk-2.1.0.dist-info/entry_points.txt
station_service_sdk-2.1.0.dist-info/RECORD
